sentileak/__init__.py
sentileak/analizer.py
sentileak/dataloader.py
sentileak/data/es/boosters.csv
sentileak/data/es/negations.csv
sentileak/data/es/sentiment_words.csv
SentiLeak-0.1.4.dist-info/LICENSE
SentiLeak-0.1.4.dist-info/METADATA
SentiLeak-0.1.4.dist-info/WHEEL
SentiLeak-0.1.4.dist-info/top_level.txt
SentiLeak-0.1.4.dist-info/RECORD
