Metadata-Version: 2.1
Name: SentiLeak
Version: 0.1.4
Summary: A lexicon-based sentiment analysis for Spanish.
Home-page: https://github.com/FernanOrtega
Author: FernanOrtega
Author-email: f.ortega.gallego@gmail.com
License: License :: OSI Approved :: GNU General Public License v3 (GPLv3)
Platform: UNKNOWN
Requires-Dist: SpaCy (<3.5,>=3.4.1)
Requires-Dist: numpy (<1.22,>=1.21.6)
Requires-Dist: snowballstemmer (<2.3,>=2.2.0)
